{
    "required": true,
    "minVersion": "0.8",
    "package": "dev.deepslate.fallacy.mixin",
    "compatibilityLevel": "JAVA_8",
    "refmap": "Fallacy.refmap.json",
    "mixins": [
        "ArmorSlotMixin",
        "CombatRulesMixin",
        "CreeperMixin",
        "EnchantmentMixin",
        "EquipableMixin",
        "LevelChunkMixin",
        "LivingEntityMixin",
        "NearestAttackableTargetGoalMixin",
        "ServerLevelHeatMixin",
        "item.ItemExtensionMixin",
        "item.ItemStackMixin",
        "player.PlayerMixin"
    ],
    "client": [
        "client.ItemStackMixin",
        "client.PlayerRenderMixin"
    ],
    "injectors": {
        "defaultRequire": 1
    }
}
